astromy_ds9/__init__.py
astromy_ds9/__version__.py
astromy_ds9-1.0.1.dist-info/LICENSE
astromy_ds9-1.0.1.dist-info/METADATA
astromy_ds9-1.0.1.dist-info/WHEEL
astromy_ds9-1.0.1.dist-info/top_level.txt
astromy_ds9-1.0.1.dist-info/RECORD
