Metadata-Version: 2.1
Name: astromy-ds9
Version: 1.0.1
Summary: Reproducing SAOImageDS9 Colormap in Python
Home-page: https://github.com/lmytime/Reproduce_DS9_colormap_in_Python
Author: Mingyu Li
Author-email: lmytime@hotmail.com
License: MIT
Classifier: License :: OSI Approved :: MIT License
Classifier: Programming Language :: Python
Classifier: Programming Language :: Python :: 3
Classifier: Programming Language :: Python :: 3.6
Classifier: Programming Language :: Python :: Implementation :: CPython
Classifier: Programming Language :: Python :: Implementation :: PyPy
Requires-Python: >=3.6.0
License-File: LICENSE
Requires-Dist: astropy
Requires-Dist: numpy
